{
    "$schema": "https://mintlify.com/docs.json",
    "theme": "maple",
    "name": "Huckle Docs",
    "colors": {
        "primary": "#46276B",
        "light": "#E3A2C5",
        "dark": "#46276B"
    },
    "appearance": {
        "default": "light",
        "strict": false
    },
    "background": {
        "decoration": "windows"
    },
    "favicon": "/favicon-image.png",
    "navigation": {
        "dropdowns": [
            {
                "dropdown": "Data Dictionary",
                "icon": "book-atlas",
                "groups": [
                    {
                        "group": "Overview",
                        "pages": [
                            "dicts/data-dictionary"
                        ]
                    },
                    {
                        "group": "By Category",
                        "pages": [
                            "dicts/primary-fields",
                            "dicts/geographic-fields",
                            "dicts/telephone-fields",
                            "dicts/household-fields",
                            "dicts/real-estate-fields",
                            "dicts/market-share-fields",
                            "dicts/consumer-passions-fields",
                            "dicts/connex-cluster-fields",
                            "dicts/connex-target-fields",
                            "dicts/census-fields"
                          
                            
                        ]
                    },
                    {
                        "group": "By Industry",
                        "pages": [
                            "dicts/recommend/cpg-fields",
                            "dicts/recommend/d2c-fields",
                            "dicts/recommend/healthcare-fields",
                            "dicts/recommend/home-health-fields",
                            "dicts/recommend/home-services-fields"
                        ]
                    }
                ]
            },
            {
                "dropdown": "User Guides",
                "icon": "arrow-progress",
                "groups": [
                    {
                        "group": "Features",
                        "pages": [
                            "user-guides/use-cases/ai-insights"
                        ]
                    },
                    {
                        "group": "Use Cases",
                        "pages": [
                            "user-guides/use-cases/ai-insights",
                            "user-guides/use-cases/campaign-strategy",
                            "user-guides/use-cases/targeted-marketing",
                            "user-guides/use-cases/persona-generation",
                            "user-guides/use-cases/crm-enrichment"
                        ]
                    }
                ]
            },
            {
                "dropdown": "API reference",
                "icon": "webhook",
                "groups": [
                    {
                        "group": "API documentation",
                        "pages": [
                            "api-reference/introduction"
                        ]
                    },
                    {
                        "group": "Endpoint examples",
                        "pages": [
                            "api-reference/endpoint/get",
                            "api-reference/endpoint/create",
                            "api-reference/endpoint/delete",
                            "api-reference/endpoint/webhook"
                        ]
                    }
                ]
            }
        ]
    },
    "logo": {
        "light": "/logo/light-large.svg",
        "dark": "/logo/dark-large.svg"
    },
    "footer": {
        "socials": {
            "linkedin": "https://www.linkedin.com/company/huckle-inc/"
        }
    }
}